[
    {
        "timestamp": 152881,
        "packetCount": 144,
        "baterryVoltage": 1.101075291633606,
        "memUsage": 445,
        "gy": true,
        "dht": true,
        "gps": true,
        "sd": true
    },
    {
        "timestamp": 159244,
        "packetCount": 150,
        "baterryVoltage": 1.101075291633606,
        "memUsage": 445,
        "gy": true,
        "dht": true,
        "gps": true,
        "sd": true
    },
    {
        "timestamp": 165602,
        "packetCount": 156,
        "baterryVoltage": 1.101075291633606,
        "memUsage": 445,
        "gy": true,
        "dht": true,
        "gps": true,
        "sd": true
    },
    {
        "timestamp": 171962,
        "packetCount": 162,
        "baterryVoltage": 1.101075291633606,
        "memUsage": 445,
        "gy": true,
        "dht": true,
        "gps": true,
        "sd": true
    },
    {
        "timestamp": 178320,
        "packetCount": 168,
        "baterryVoltage": 1.101075291633606,
        "memUsage": 445,
        "gy": true,
        "dht": true,
        "gps": true,
        "sd": true
    },
    {
        "timestamp": 184681,
        "packetCount": 174,
        "baterryVoltage": 1.101075291633606,
        "memUsage": 445,
        "gy": true,
        "dht": true,
        "gps": true,
        "sd": true
    },
    {
        "timestamp": 191042,
        "packetCount": 180,
        "baterryVoltage": 1.101075291633606,
        "memUsage": 445,
        "gy": true,
        "dht": true,
        "gps": true,
        "sd": true
    },
    {
        "timestamp": 197406,
        "packetCount": 186,
        "baterryVoltage": 1.101075291633606,
        "memUsage": 445,
        "gy": true,
        "dht": true,
        "gps": true,
        "sd": true
    },
    {
        "timestamp": 203771,
        "packetCount": 192,
        "baterryVoltage": 1.101075291633606,
        "memUsage": 445,
        "gy": true,
        "dht": true,
        "gps": true,
        "sd": true
    },
    {
        "timestamp": 210132,
        "packetCount": 198,
        "baterryVoltage": 1.101075291633606,
        "memUsage": 445,
        "gy": true,
        "dht": true,
        "gps": true,
        "sd": true
    },
    {
        "timestamp": 216495,
        "packetCount": 204,
        "baterryVoltage": 1.101075291633606,
        "memUsage": 445,
        "gy": true,
        "dht": true,
        "gps": true,
        "sd": true
    },
    {
        "timestamp": 222858,
        "packetCount": 210,
        "baterryVoltage": 1.101075291633606,
        "memUsage": 445,
        "gy": true,
        "dht": true,
        "gps": true,
        "sd": true
    },
    {
        "timestamp": 229216,
        "packetCount": 216,
        "baterryVoltage": 1.101075291633606,
        "memUsage": 445,
        "gy": true,
        "dht": true,
        "gps": true,
        "sd": true
    },
    {
        "timestamp": 235578,
        "packetCount": 222,
        "baterryVoltage": 1.101075291633606,
        "memUsage": 445,
        "gy": true,
        "dht": true,
        "gps": true,
        "sd": true
    },
    {
        "timestamp": 241937,
        "packetCount": 228,
        "baterryVoltage": 1.101075291633606,
        "memUsage": 445,
        "gy": true,
        "dht": true,
        "gps": true,
        "sd": true
    },
    {
        "timestamp": 248299,
        "packetCount": 234,
        "baterryVoltage": 1.101075291633606,
        "memUsage": 445,
        "gy": true,
        "dht": true,
        "gps": true,
        "sd": true
    },
    {
        "timestamp": 254660,
        "packetCount": 240,
        "baterryVoltage": 1.101075291633606,
        "memUsage": 445,
        "gy": true,
        "dht": true,
        "gps": true,
        "sd": true
    },
    {
        "timestamp": 261026,
        "packetCount": 246,
        "baterryVoltage": 1.101075291633606,
        "memUsage": 445,
        "gy": true,
        "dht": true,
        "gps": true,
        "sd": true
    },
    {
        "timestamp": 267392,
        "packetCount": 252,
        "baterryVoltage": 1.101075291633606,
        "memUsage": 445,
        "gy": true,
        "dht": true,
        "gps": true,
        "sd": true
    },
    {
        "timestamp": 273753,
        "packetCount": 258,
        "baterryVoltage": 1.101075291633606,
        "memUsage": 445,
        "gy": true,
        "dht": true,
        "gps": true,
        "sd": true
    },
    {
        "timestamp": 280115,
        "packetCount": 264,
        "baterryVoltage": 1.101075291633606,
        "memUsage": 445,
        "gy": true,
        "dht": true,
        "gps": true,
        "sd": true
    },
    {
        "timestamp": 286474,
        "packetCount": 270,
        "baterryVoltage": 1.101075291633606,
        "memUsage": 445,
        "gy": true,
        "dht": true,
        "gps": true,
        "sd": true
    },
    {
        "timestamp": 292835,
        "packetCount": 276,
        "baterryVoltage": 1.101075291633606,
        "memUsage": 445,
        "gy": true,
        "dht": true,
        "gps": true,
        "sd": true
    },
    {
        "timestamp": 299193,
        "packetCount": 282,
        "baterryVoltage": 1.101075291633606,
        "memUsage": 445,
        "gy": true,
        "dht": true,
        "gps": true,
        "sd": true
    },
    {
        "timestamp": 305553,
        "packetCount": 288,
        "baterryVoltage": 1.101075291633606,
        "memUsage": 445,
        "gy": true,
        "dht": true,
        "gps": true,
        "sd": true
    },
    {
        "timestamp": 311912,
        "packetCount": 294,
        "baterryVoltage": 1.101075291633606,
        "memUsage": 445,
        "gy": true,
        "dht": true,
        "gps": true,
        "sd": true
    },
    {
        "timestamp": 318274,
        "packetCount": 300,
        "baterryVoltage": 1.101075291633606,
        "memUsage": 445,
        "gy": true,
        "dht": true,
        "gps": true,
        "sd": true
    },
    {
        "timestamp": 324637,
        "packetCount": 306,
        "baterryVoltage": 1.101075291633606,
        "memUsage": 445,
        "gy": true,
        "dht": true,
        "gps": true,
        "sd": true
    },
    {
        "timestamp": 331004,
        "packetCount": 312,
        "baterryVoltage": 1.101075291633606,
        "memUsage": 445,
        "gy": true,
        "dht": true,
        "gps": true,
        "sd": true
    },
    {
        "timestamp": 337368,
        "packetCount": 318,
        "baterryVoltage": 1.101075291633606,
        "memUsage": 445,
        "gy": true,
        "dht": true,
        "gps": true,
        "sd": true
    },
    {
        "timestamp": 343769,
        "packetCount": 324,
        "baterryVoltage": 1.101075291633606,
        "memUsage": 445,
        "gy": true,
        "dht": true,
        "gps": true,
        "sd": true
    },
    {
        "timestamp": 350130,
        "packetCount": 330,
        "baterryVoltage": 1.101075291633606,
        "memUsage": 445,
        "gy": true,
        "dht": true,
        "gps": true,
        "sd": true
    },
    {
        "timestamp": 356491,
        "packetCount": 336,
        "baterryVoltage": 1.101075291633606,
        "memUsage": 445,
        "gy": true,
        "dht": true,
        "gps": true,
        "sd": true
    },
    {
        "timestamp": 362849,
        "packetCount": 342,
        "baterryVoltage": 1.101075291633606,
        "memUsage": 445,
        "gy": true,
        "dht": true,
        "gps": true,
        "sd": true
    },
    {
        "timestamp": 369228,
        "packetCount": 348,
        "baterryVoltage": 1.101075291633606,
        "memUsage": 445,
        "gy": true,
        "dht": true,
        "gps": true,
        "sd": true
    },
    {
        "timestamp": 375604,
        "packetCount": 354,
        "baterryVoltage": 1.101075291633606,
        "memUsage": 445,
        "gy": true,
        "dht": true,
        "gps": true,
        "sd": true
    },
    {
        "timestamp": 381980,
        "packetCount": 360,
        "baterryVoltage": 1.101075291633606,
        "memUsage": 445,
        "gy": true,
        "dht": true,
        "gps": true,
        "sd": true
    },
    {
        "timestamp": 388356,
        "packetCount": 366,
        "baterryVoltage": 1.101075291633606,
        "memUsage": 445,
        "gy": true,
        "dht": true,
        "gps": true,
        "sd": true
    },
    {
        "timestamp": 394731,
        "packetCount": 372,
        "baterryVoltage": 1.101075291633606,
        "memUsage": 445,
        "gy": true,
        "dht": true,
        "gps": true,
        "sd": true
    },
    {
        "timestamp": 401106,
        "packetCount": 378,
        "baterryVoltage": 1.101075291633606,
        "memUsage": 445,
        "gy": true,
        "dht": true,
        "gps": true,
        "sd": true
    },
    {
        "timestamp": 407483,
        "packetCount": 384,
        "baterryVoltage": 1.101075291633606,
        "memUsage": 445,
        "gy": true,
        "dht": true,
        "gps": true,
        "sd": true
    }
]